sbo_sphinx/__init__.py
sbo_sphinx/apidoc.py
sbo_sphinx/conf.py
sbo_sphinx/jsdoc.py
sbo_sphinx/_static/favicon.ico
sbo_sphinx/_static/safari_cover.png
sbo_sphinx/_static/safari_logo.png
sbo_sphinx/jsdoc-toolkit/changes.txt
sbo_sphinx/jsdoc-toolkit/jsdebug.jar
sbo_sphinx/jsdoc-toolkit/jsrun.jar
sbo_sphinx/jsdoc-toolkit/jsrun.sh
sbo_sphinx/jsdoc-toolkit/README.txt
sbo_sphinx/jsdoc-toolkit/app/frame.js
sbo_sphinx/jsdoc-toolkit/app/main.js
sbo_sphinx/jsdoc-toolkit/app/run.js
sbo_sphinx/jsdoc-toolkit/app/test.js
sbo_sphinx/jsdoc-toolkit/app/frame/Chain.js
sbo_sphinx/jsdoc-toolkit/app/frame/Dumper.js
sbo_sphinx/jsdoc-toolkit/app/frame/Hash.js
sbo_sphinx/jsdoc-toolkit/app/frame/Link.js
sbo_sphinx/jsdoc-toolkit/app/frame/Namespace.js
sbo_sphinx/jsdoc-toolkit/app/frame/Opt.js
sbo_sphinx/jsdoc-toolkit/app/frame/Reflection.js
sbo_sphinx/jsdoc-toolkit/app/frame/String.js
sbo_sphinx/jsdoc-toolkit/app/frame/Testrun.js
sbo_sphinx/jsdoc-toolkit/app/handlers/FOODOC.js
sbo_sphinx/jsdoc-toolkit/app/handlers/XMLDOC.js
sbo_sphinx/jsdoc-toolkit/app/handlers/XMLDOC/DomReader.js
sbo_sphinx/jsdoc-toolkit/app/handlers/XMLDOC/XMLDoc.js
sbo_sphinx/jsdoc-toolkit/app/handlers/XMLDOC/XMLParse.js
sbo_sphinx/jsdoc-toolkit/app/lib/JSDOC.js
sbo_sphinx/jsdoc-toolkit/app/lib/JSDOC/DocComment.js
sbo_sphinx/jsdoc-toolkit/app/lib/JSDOC/DocTag.js
sbo_sphinx/jsdoc-toolkit/app/lib/JSDOC/JsDoc.js
sbo_sphinx/jsdoc-toolkit/app/lib/JSDOC/JsPlate.js
sbo_sphinx/jsdoc-toolkit/app/lib/JSDOC/Lang.js
sbo_sphinx/jsdoc-toolkit/app/lib/JSDOC/Parser.js
sbo_sphinx/jsdoc-toolkit/app/lib/JSDOC/PluginManager.js
sbo_sphinx/jsdoc-toolkit/app/lib/JSDOC/Symbol.js
sbo_sphinx/jsdoc-toolkit/app/lib/JSDOC/SymbolSet.js
sbo_sphinx/jsdoc-toolkit/app/lib/JSDOC/TextStream.js
sbo_sphinx/jsdoc-toolkit/app/lib/JSDOC/Token.js
sbo_sphinx/jsdoc-toolkit/app/lib/JSDOC/TokenReader.js
sbo_sphinx/jsdoc-toolkit/app/lib/JSDOC/TokenStream.js
sbo_sphinx/jsdoc-toolkit/app/lib/JSDOC/Util.js
sbo_sphinx-2.2.0.dist-info/DESCRIPTION.rst
sbo_sphinx-2.2.0.dist-info/METADATA
sbo_sphinx-2.2.0.dist-info/metadata.json
sbo_sphinx-2.2.0.dist-info/RECORD
sbo_sphinx-2.2.0.dist-info/top_level.txt
sbo_sphinx-2.2.0.dist-info/WHEEL
