Metadata-Version: 2.0
Name: sbo-sphinx
Version: 2.2.0
Summary: Sphinx configuration and libraries for Safari Books Online documentation
Home-page: http://github.com/safarijv/sbo-sphinx
Author: Jeremy Bowman
Author-email: jbowman@safaribooksonline.com
License: UNKNOWN
Platform: UNKNOWN
Classifier: Development Status :: 5 - Production/Stable
Classifier: Environment :: Console
Classifier: Intended Audience :: Developers
Classifier: License :: OSI Approved :: BSD License
Classifier: Natural Language :: English
Classifier: Operating System :: OS Independent
Classifier: Programming Language :: Python :: 2.7
Classifier: Programming Language :: Python :: 3
Classifier: Programming Language :: Python :: 3.4
Classifier: Topic :: Documentation
Classifier: Topic :: Software Development :: Documentation
Requires-Dist: setuptools
Requires-Dist: pip
Requires-Dist: six
Requires-Dist: html5lib
Requires-Dist: bleach
Requires-Dist: docutils
Requires-Dist: Pygments
Requires-Dist: pytz
Requires-Dist: MarkupSafe
Requires-Dist: PyStemmer
Requires-Dist: Babel
Requires-Dist: Jinja2
Requires-Dist: snowballstemmer
Requires-Dist: readme
Requires-Dist: recommonmark
Requires-Dist: Sphinx
Requires-Dist: alabaster
Requires-Dist: sphinx-rtd-theme
